mycalc/calculator.py
jooni0227-0.0.1.dist-info/METADATA
jooni0227-0.0.1.dist-info/WHEEL
jooni0227-0.0.1.dist-info/top_level.txt
jooni0227-0.0.1.dist-info/RECORD
