Metadata-Version: 2.1
Name: jooni0227
Version: 0.0.1
Summary: oss-dev my cacluator 0001
Home-page: https://github.com/chunsejin/abc
Download-URL: https://github.com/chunsejin/abc/egfc.zip
Author: jooni0227
Author-email: joone022762@gmail.com
License: UNKNOWN
Platform: UNKNOWN
